{
  "slug": "base44-customer-support-what-to-expect",
  "title": "Base44 Customer Support: What to Expect",
  "metaDescription": "Learn about Base44 Customer Support: What to Expect and how Base44 helps you build apps without coding.",
  "keywords": [
    "Base44",
    "no-code",
    "app builder"
  ],
  "body": "<h1>Base44 Customer Support: What to Expect</h1><p>Content generation failed. Please retry.</p>",
  "generatedAt": "2026-05-17T13:33:45.603Z",
  "error": "429 {\"error\":{\"message\":\"Rate limit reached for model `llama-3.3-70b-versatile` in organization `org_01kr6z3sjgecs8shrayk681re9` service tier `on_demand` on tokens per day (TPD): Limit 100000, Used 99312, Requested 2304. Please try again in 23m16.224s. Need more tokens? Upgrade to Dev Tier today at https://console.groq.com/settings/billing\",\"type\":\"tokens\",\"code\":\"rate_limit_exceeded\"}}"
}