{
  "slug": "build-an-rfq-manager-without-coding-using-base44",
  "title": "Build an RFQ Manager Without Coding Using Base44",
  "metaDescription": "Build an RFQ Manager without coding using Base44, a no-code app builder, and streamline your procurement process.",
  "keywords": [
    "no-code app builder",
    "RFQ manager",
    "procurement software",
    "request for quote",
    "Base44 platform"
  ],
  "body": "<p><strong>Build an RFQ Manager Without Coding Using Base44</strong></p>\n<p>In today&#39;s fast-paced business environment, managing request for quote (RFQ) processes efficiently is crucial for organizations to stay competitive. However, traditional RFQ management often involves manual data entry, paperwork, and communication hassles, consuming valuable time and resources. This is where no-code app builders like Base44 come into play, offering a game-changing solution to streamline procurement processes.</p>\n<p><strong>What is a Request for Quote (RFQ) Manager?</strong></p>\n<p>A Request for Quote (RFQ) manager is a system designed to handle RFQs efficiently, from initial quote requests to awarding contracts. It typically includes features such as quote management, vendor communication, and evaluation tools. A well-designed RFQ manager helps organizations make informed purchasing decisions, reduce procurement costs, and improve relationships with suppliers.</p>\n<p><strong>Challenges of Traditional RFQ Management</strong></p>\n<p>Traditional RFQ management often involves:</p>\n<ul>\n<li>Manual data entry and paperwork</li>\n<li>Time-consuming communication with vendors</li>\n<li>Difficulty in evaluating and comparing quotes</li>\n<li>High risk of human error and data inconsistencies</li>\n<li>Limited visibility into procurement processes</li>\n</ul>\n<p><strong>How Base44 Can Help</strong></p>\n<p>Base44, a leading no-code app builder, enables you to build a custom RFQ manager without coding, ensuring a seamless and efficient procurement process. With Base44, you can:</p>\n<ul>\n<li>Create a user-friendly interface for quote submissions and vendor communication</li>\n<li>Automate data entry and quote evaluation using customizable workflows</li>\n<li>Integrate with existing systems and databases for seamless data synchronization</li>\n<li>Set up notifications and alerts for timely decision-making</li>\n<li>Visualize procurement data for informed decision-making</li>\n</ul>\n<p><strong>Benefits of Using Base44 for RFQ Management</strong></p>\n<p>By leveraging Base44 to build your RFQ manager, you can:</p>\n<ul>\n<li><strong>Save time</strong>: Automate manual tasks and reduce paperwork</li>\n<li><strong>Improve accuracy</strong>: Minimize human error and ensure data consistency</li>\n<li><strong>Boost productivity</strong>: Streamline procurement processes and make informed decisions</li>\n<li><strong>Enhance vendor relationships</strong>: Improve communication and collaboration with suppliers</li>\n<li><strong>Gain insights</strong>: Visualize procurement data for better decision-making</li>\n</ul>\n<p><strong>How to Build an RFQ Manager with Base44</strong></p>\n<p>Building an RFQ manager with Base44 involves a straightforward process:</p>\n<ol>\n<li><strong>Sign up for Base44</strong>: Try Base44 Free and start building your RFQ manager today. <a href=\"https://base44.pxf.io/c/2252709/2049275/25619?trafcat=base\" class=\"cta-link\">Start Building with Base44 →</a></li>\n<li><strong>Design your app</strong>: Use Base44&#39;s drag-and-drop interface to create a custom RFQ manager that meets your needs.</li>\n<li><strong>Configure workflows</strong>: Automate data entry, quote evaluation, and communication with vendors using customizable workflows.</li>\n<li><strong>Integrate with existing systems</strong>: Seamlessly integrate with your existing systems and databases for data synchronization.</li>\n<li><strong>Launch and refine</strong>: Launch your RFQ manager and continuously refine it based on user feedback and performance metrics.</li>\n</ol>\n<p><strong>Real-World Applications of RFQ Management with Base44</strong></p>\n<p>Base44&#39;s RFQ management capabilities can be applied across various industries, including:</p>\n<ul>\n<li><strong>Construction</strong>: Streamline procurement processes for construction materials and services</li>\n<li><strong>Manufacturing</strong>: Manage RFQs for equipment, raw materials, and services</li>\n<li><strong>Healthcare</strong>: Automate procurement processes for medical supplies and services</li>\n<li><strong>Government</strong>: Simplify RFQ management for public procurement processes</li>\n</ul>\n<p><strong>Conclusion</strong></p>\n<p>Building an RFQ manager without coding using Base44 empowers organizations to streamline their procurement processes, improve accuracy, and enhance vendor relationships. By leveraging Base44&#39;s no-code app builder, you can create a custom RFQ manager that meets your specific needs and drives business success. Start building with Base44 today and experience the benefits of efficient RFQ management. <a href=\"https://base44.pxf.io/c/2252709/2049275/25619?trafcat=base\" class=\"cta-link\">Start Building with Base44 →</a></p>\n<p>Note: Replace <a href=\"https://base44.pxf.io/c/2252709/2049275/25619?trafcat=base\" class=\"cta-link\">Start Building with Base44 →</a> with the actual affiliate link to Base44.</p>\n",
  "generatedAt": "2026-05-22T00:27:58.224Z"
}