{
  "slug": "charging-monthly-fees-for-base44-apps-you-build",
  "title": "Charging Monthly Fees for Base44 Apps You Build",
  "metaDescription": "Learn about Charging Monthly Fees for Base44 Apps You Build and how Base44 helps you build apps without coding.",
  "keywords": [
    "Base44",
    "no-code",
    "app builder"
  ],
  "body": "<h1>Charging Monthly Fees for Base44 Apps You Build</h1><p>Content generation failed. Please retry.</p>",
  "generatedAt": "2026-05-17T23:49:35.638Z",
  "error": "429 Tokens per day limit exceeded - too many tokens processed."
}