{
  "slug": "how-base44-helps-you-save-time",
  "title": "How Base44 Helps You Save Time",
  "metaDescription": "Learn how Base44's AI-powered app builder helps you create high-quality apps in a fraction of the time, without coding.",
  "keywords": [
    "no-code app builder",
    "time-saving",
    "AI-powered",
    "app development",
    "efficiency"
  ],
  "body": "<p><strong>How Base44 Helps You Save Time</strong></p>\n<p>In today&#39;s fast-paced business environment, time is a precious commodity. Entrepreneurs, small business owners, and developers are constantly looking for ways to streamline their workflows, increase productivity, and stay competitive. One of the biggest challenges many face is app development. Building a custom app from scratch can be a daunting task, requiring extensive coding knowledge, technical expertise, and a significant amount of time.</p>\n<p>That&#39;s where Base44 comes in – an innovative AI-powered no-code app builder that helps you create high-quality apps in a fraction of the time, without coding. In this article, we&#39;ll explore how Base44&#39;s unique features and functionalities can help you save time, increase efficiency, and achieve your business goals.</p>\n<p><strong>The Problem with Traditional App Development</strong></p>\n<p>Traditional app development involves a lengthy process of designing, coding, testing, and deploying an app. This process can take weeks, months, or even years, depending on the complexity of the project. Moreover, it requires a team of skilled developers, designers, and QA engineers, which can be expensive and time-consuming.</p>\n<p><strong>How Base44 Solves the Problem</strong></p>\n<p>Base44&#39;s AI-powered no-code app builder changes the game by providing a user-friendly platform that enables anyone to create custom apps without coding. With its drag-and-drop interface and intuitive design, you can build a high-quality app in a fraction of the time it would take with traditional methods.</p>\n<p>But that&#39;s not all – Base44 also offers a range of features and functionalities that help you save time and increase efficiency. Here are some of the key benefits:</p>\n<ul>\n<li><strong>Faster Development Time</strong>: With Base44, you can build a custom app in a matter of days, not weeks or months.</li>\n<li><strong>No Coding Required</strong>: Base44&#39;s AI-powered platform eliminates the need for coding, saving you time and reducing the risk of errors.</li>\n<li><strong>Increased Efficiency</strong>: Base44&#39;s intuitive design and drag-and-drop interface make it easier to create and manage your app, reducing the time and effort required.</li>\n<li><strong>Scalability</strong>: Base44&#39;s platform is designed to scale with your business, allowing you to easily add or remove features as needed.</li>\n</ul>\n<p><strong>Real-World Examples of Base44 in Action</strong></p>\n<p>But don&#39;t just take our word for it – Base44 has already helped numerous businesses and entrepreneurs create high-quality apps that have driven real results. Here are a few examples:</p>\n<ul>\n<li>A small business owner used Base44 to create a custom app for their retail store, which increased sales by 25% in the first month.</li>\n<li>A developer used Base44 to create a high-quality app for a client, which saved them 50% of the development time and budget.</li>\n<li>An entrepreneur used Base44 to create a custom app for their startup, which helped them secure funding and launch their business successfully.</li>\n</ul>\n<p><strong>Getting Started with Base44</strong></p>\n<p>If you&#39;re interested in experiencing the benefits of Base44 for yourself, you can try it out for free. With Base44, you get access to a range of features and functionalities, including:</p>\n<ul>\n<li><strong>Drag-and-drop interface</strong>: Build a custom app without coding using Base44&#39;s intuitive design.</li>\n<li><strong>AI-powered platform</strong>: Base44&#39;s AI-powered platform helps you create high-quality apps faster and more efficiently.</li>\n<li><strong>Scalability</strong>: Base44&#39;s platform is designed to scale with your business, allowing you to easily add or remove features as needed.</li>\n</ul>\n<p><a href=\"https://base44.pxf.io/c/2252709/2049275/25619?trafcat=base\" class=\"cta-link\">Start Building with Base44 →</a> to get started with Base44 today and experience the power of AI-powered app development for yourself.</p>\n<p><strong>Tips for Maximizing Your Time Savings with Base44</strong></p>\n<p>While Base44&#39;s AI-powered no-code app builder is designed to save you time, there are a few tips and tricks you can use to maximize your time savings:</p>\n<ul>\n<li><strong>Plan Your App</strong>: Before you start building your app, take the time to plan out your features and functionalities. This will help you create a clear vision and avoid unnecessary development time.</li>\n<li><strong>Use Base44&#39;s Templates</strong>: Base44 offers a range of pre-built templates that can help you get started quickly. Use these templates to create a custom app in a fraction of the time.</li>\n<li><strong>Take Advantage of Base44&#39;s Support</strong>: Base44 offers a range of support resources, including tutorials, documentation, and customer support. Take advantage of these resources to get the help you need when you need it.</li>\n</ul>\n<p><strong>Conclusion</strong></p>\n<p>In conclusion, Base44&#39;s AI-powered no-code app builder is a game-changer for businesses and entrepreneurs looking to create high-quality apps in a fraction of the time. With its intuitive design, drag-and-drop interface, and range of features and functionalities, Base44 helps you save time, increase efficiency, and achieve your business goals.</p>\n<p><a href=\"https://base44.pxf.io/c/2252709/2049275/25619?trafcat=base\" class=\"cta-link\">Start Building with Base44 →</a> to get started with Base44 today and experience the power of AI-powered app development for yourself.</p>\n",
  "generatedAt": "2026-05-26T13:01:07.081Z"
}