{
  "slug": "how-dermatologists-use-base44-for-scheduling",
  "title": "How Dermatologists Use Base44 for Scheduling",
  "metaDescription": "Learn about How Dermatologists Use Base44 for Scheduling and how Base44 helps you build apps without coding.",
  "keywords": [
    "Base44",
    "no-code",
    "app builder"
  ],
  "body": "<h1>How Dermatologists Use Base44 for Scheduling</h1><p>Content generation failed. Please retry.</p>",
  "generatedAt": "2026-07-07T23:17:03.832Z",
  "error": "429 {\"error\":{\"message\":\"Rate limit reached for model `llama-3.3-70b-versatile` in organization `org_01kr6z3sjgecs8shrayk681re9` service tier `on_demand` on tokens per day (TPD): Limit 100000, Used 98208, Requested 2304. Please try again in 7m22.368s. Need more tokens? Upgrade to Dev Tier today at https://console.groq.com/settings/billing\",\"type\":\"tokens\",\"code\":\"rate_limit_exceeded\"}}"
}