{
  "slug": "senior-build-an-etsy-shop-management-tool-advanced",
  "title": "Build an Etsy Shop Management Tool - Advanced Strategies",
  "metaDescription": "Learn how to build an etsy shop management tool with Base44 - no coding required.",
  "keywords": [
    "Base44",
    "seniors",
    "no-code",
    "app builder"
  ],
  "body": "<h1>Mastering Base44 for Advanced Results</h1>\n\n<p>As a senior, you're likely no stranger to the world of software and technology. But even with years of experience, staying up-to-date with the latest tools and features can be a daunting task. In this article, we'll dive into the advanced strategies and techniques for getting the most out of Base44, a powerful tool that's often misunderstood or underutilized.</p>\n\n<h2>Why You Can Do This</h2>\n\n<p>When it comes to mastering Base44, it's easy to feel intimidated. After all, this is a complex tool with a steep learning curve. But the truth is, anyone can learn to use Base44 effectively, regardless of age or technical expertise. With practice and patience, you can unlock its full potential and achieve advanced results.</p>\n\n<p>Base44 is a versatile tool that can be used for a wide range of tasks, from automating repetitive processes to scaling complex systems. By mastering its advanced features, you can save time, increase productivity, and achieve greater success in your personal and professional life.</p>\n\n<h2>Section 1: Scaling with Base44</h2>\n\n<p>One of the most powerful features of Base44 is its ability to scale complex systems. By using advanced techniques such as data modeling and workflow automation, you can efficiently manage large amounts of data and streamline your workflows.</p>\n\n<p>When scaling with Base44, it's essential to focus on data modeling. This involves creating a clear and logical structure for your data, which enables you to easily manage and analyze it. By using advanced data modeling techniques, you can create a scalable system that can handle large amounts of data and support complex workflows.</p>\n\n<p>Another key aspect of scaling with Base44 is workflow automation. By automating repetitive tasks and processes, you can free up time and resources for more strategic activities. With advanced workflow automation techniques, you can create complex workflows that can be easily managed and scaled.</p>\n\n<h2>Section 2: Advanced Features and Techniques</h2>\n\n<p>Base44 has a wide range of advanced features and techniques that can help you achieve greater results. Some of the most useful include:</p>\n\n<ul>\n  <li><strong>Data validation and error handling:</strong> Use advanced data validation techniques to ensure that your data is accurate and complete. By implementing error handling, you can identify and correct errors quickly and efficiently.</li>\n  <li><strong>Conditional logic and decision-making:</strong> Use advanced conditional logic techniques to make complex decisions based on your data. By using decision-making tools, you can automate complex workflows and improve efficiency.</li>\n  <li><strong>Real-time analytics and reporting:</strong> Use advanced analytics and reporting techniques to gain insights into your data and make data-driven decisions. By using real-time analytics, you can stay ahead of the curve and make informed decisions.</li>\n</ul>\n\n<h2>Section 3: Maximizing Productivity with Automation</h2>\n\n<p>One of the most significant benefits of using Base44 is the ability to automate repetitive tasks and processes. By automating tasks, you can free up time and resources for more strategic activities and achieve greater productivity.</p>\n\n<p>When automating with Base44, it's essential to focus on the following key areas:</p>\n\n<ul>\n  <li><strong>Task automation:</strong> Automate repetitive tasks such as data entry, reporting, and workflows. By automating tasks, you can free up time and resources for more strategic activities.</li>\n  <li><strong>Process automation:</strong> Automate complex processes such as data modeling, workflow management, and analytics. By automating processes, you can improve efficiency and scalability.</li>\n  <li><strong>System automation:</strong> Automate entire systems, including data management, workflow management, and analytics. By automating systems, you can achieve greater efficiency and scalability.</li>\n</ul>\n\n<p><a href=\"https://base44.pxf.io/c/2252709/2049275/25619?trafcat=base\"><strong>Try Base44 free today.</strong></a></p>\n<h2>Take Your Base44 Skills to the Next Level</h2>\n\n<p>Are you ready to unlock the full potential of Base44? Our expert training programs are designed to help you master advanced techniques and strategies for achieving greater results. With our guidance, you can:</p>\n\n<ul>\n  <li><strong>Master data modeling and workflow automation:</strong> Learn advanced techniques for managing and analyzing complex data and workflows.</li>\n  <li><strong>Unlock advanced features and techniques:</strong> Discover how to use advanced features such as data validation, conditional logic, and real-time analytics.</li>\n  <li><strong>Maximize productivity with automation:</strong> Learn how to automate repetitive tasks, processes, and systems for greater efficiency and scalability.</li>\n</ul>\n\n<p>Don't wait – take the first step towards mastering Base44 today!</p>\n\n<h2>Section 4: Advanced Tips and Tricks</h2>\n\n<p>When it comes to using Base44, there are a number of advanced tips and tricks that can help you achieve greater results. Some of the most useful include:</p>\n\n<ul>\n  <li><strong>Using advanced data visualization techniques:</strong> Use advanced data visualization techniques to gain insights into your data and make data-driven decisions.</li>\n  <li><strong>Implementing advanced security measures:</strong> Use advanced security measures to protect your data and systems from unauthorized access.</li>\n  <li><strong>Using advanced collaboration tools:</strong> Use advanced collaboration tools to work with teams and stakeholders more effectively.</li>\n</ul>\n\n<h2>Section 5: Conclusion</h2>\n\n<p>Mastering Base44 is a journey that requires patience, practice, and persistence. By following the advanced strategies and techniques outlined in this article, you can unlock the full potential of this powerful tool and achieve greater results in your personal and professional life.</p>\n\n<p>Remember, the key to success is to stay focused, stay committed, and keep learning. With time and practice, you can master Base44 and achieve advanced results.</p>\n\n<em>Don't let complexity hold you back – take the first step towards mastering Base44 today!</em>\n\n<p><a href=\"https://base44.pxf.io/c/2252709/2049275/25619?trafcat=base\"><strong>Try Base44 free today.</strong></a></p>\n<h2>Get Started with Base44 Today</h2>\n\n<p>Are you ready to unlock the full potential of Base44? Our expert training programs are designed to help you master advanced techniques and strategies for achieving greater results. With our guidance, you can:</p>\n\n<ul>\n  <li><strong>Master data modeling and workflow automation:</strong> Learn advanced techniques for managing and analyzing complex data and workflows.</li>\n  <li><strong>Unlock advanced features and techniques:</strong> Discover how to use advanced features such as data validation, conditional logic, and real-time analytics.</li>\n  <li><strong>Maximize productivity with automation:</strong> Learn how to automate repetitive tasks, processes, and systems for greater efficiency and scalability.</li>\n</ul>\n\n<p>Don't wait – take the first step towards mastering Base44 today!</p>",
  "audience": "seniors",
  "coverImage": "https://images.pexels.com/photos/14618066/pexels-photo-14618066.jpeg?auto=compress&cs=tinysrgb&h=350",
  "generatedAt": "2026-06-09T04:39:33.481Z"
}