{
  "slug": "senior-how-to-create-a-digital-legacy-project-advanced",
  "title": "How to Create a Digital Legacy Project - Advanced Strategies",
  "metaDescription": "Learn how to how to create a digital legacy project with Base44 - no coding required.",
  "keywords": [
    "Base44",
    "seniors",
    "no-code",
    "app builder"
  ],
  "body": "<h1>Scaling Your Online Presence with Base44: Advanced Strategies for Seniors 55+</h1>\n\n<h2>Why You Can Do This</h2>\n\nAs a senior, you may think that staying online and growing your presence requires a team of experts, a huge budget, and a lot of technical know-how. But the truth is, with the right tools and a bit of know-how, you can take control of your online presence and reach a wider audience. Base44 is a powerful platform that can help you do just that. With its user-friendly interface and advanced features, you can create a robust online presence that showcases your skills, products, or services to the world.\n\n<h2>Mastering Advanced Features: A Guide to Scaling Your Online Presence</h2>\n\nAs you grow your online presence, you'll start to notice that you're generating more traffic, more leads, and more opportunities. But with more traffic comes more complexity. That's where advanced features come in. In this section, we'll explore some of the most powerful features in Base44 that can help you scale your online presence.\n\n<ul>\n  <li><strong>Content Scheduling:</strong> With Base44, you can schedule your content in advance, ensuring that your audience is always engaged and informed. This feature is especially useful for businesses with multiple locations or employees who need to post updates on behalf of the company.</li>\n  <li><strong>Content Curation:</strong> Base44 allows you to curate content from other sources, saving you time and effort. This feature is perfect for businesses that need to keep their audience informed about the latest industry trends and news.</li>\n  <li><strong>Automation Tools:</strong> With Base44, you can automate repetitive tasks, such as sending welcome emails or follow-up messages. This feature is a game-changer for businesses that need to nurture leads and customers over time.</li>\n</ul>\n\n<h2>Advanced SEO Strategies: Optimizing Your Website for Search Engines</h2>\n\nSearch Engine Optimization (SEO) is a critical component of any online marketing strategy. With Base44, you can optimize your website for search engines using advanced SEO strategies. Here are a few techniques to get you started:\n\n<ul>\n  <li><strong>Keyword Research:</strong> Use Base44's built-in keyword research tool to identify the most relevant and high-traffic keywords related to your business.</li>\n  <li><strong>On-Page Optimization:</strong> Use Base44's on-page optimization tools to optimize your website's titles, descriptions, and headings for search engines.</li>\n  <li><strong>Content Quality:</strong> Use Base44's content quality tools to ensure that your content is engaging, informative, and optimized for search engines.</li>\n</ul>\n\n<h2>Building a Community: Leveraging Social Media and Email Marketing</h2>\n\nBuilding a community around your business or brand is critical for long-term success. With Base44, you can leverage social media and email marketing to build a loyal following and drive engagement. Here are a few strategies to get you started:\n\n<ul>\n  <li><strong>Social Media Integration:</strong> Use Base44's social media integration tools to connect with your audience on multiple platforms, including Facebook, Twitter, and Instagram.</li>\n  <li><strong>Email Marketing:</strong> Use Base44's email marketing tools to send targeted campaigns to your audience, driving engagement and conversions.</li>\n  <li><strong>Community Building:</strong> Use Base44's community building tools to create a private Facebook group or forum where customers can connect with each other and share ideas.</li>\n</ul>\n\n<h2>Scaling and Automation: Taking Your Online Presence to the Next Level</h2>\n\nAs you grow your online presence, you'll start to notice that you're generating more traffic, more leads, and more opportunities. But with more traffic comes more complexity. That's where scaling and automation come in. In this section, we'll explore some of the most powerful features in Base44 that can help you scale your online presence and automate repetitive tasks.\n\n<ul>\n  <li><strong>Scalable Architecture:</strong> Base44's scalable architecture ensures that your website can handle high traffic and large volumes of data, without compromising performance.</li>\n  <li><strong>Automation Tools:</strong> With Base44, you can automate repetitive tasks, such as sending welcome emails or follow-up messages, freeing up time for more strategic activities.</li>\n  <li><strong>Advanced Analytics:</strong> Use Base44's advanced analytics tools to track your website's performance, identify areas for improvement, and make data-driven decisions.</li>\n</ul>\n\n<p><a href=\"https://base44.pxf.io/c/2252709/2049275/25619?trafcat=base\"><strong>Try Base44 free today.</strong></a></p>\nTake the first step towards scaling your online presence with Base44. Sign up for a free trial today and discover the power of advanced marketing strategies.\n\n<h2>Putting it all Together: A Final Checklist for Success</h2>\n\nScaling your online presence with Base44 requires a combination of advanced strategies, automation tools, and a willingness to adapt to changing market conditions. Here's a final checklist to help you get started:\n\n<ul>\n  <li><strong>Master Advanced Features:</strong> Take advantage of Base44's advanced features, including content scheduling, content curation, and automation tools.</li>\n  <li><strong>Optimize for SEO:</strong> Use Base44's SEO tools to optimize your website for search engines and improve your online visibility.</li>\n  <li><strong>Build a Community:</strong> Leverage social media and email marketing to build a loyal following and drive engagement.</li>\n  <li><strong>Scale and Automate:</strong> Use Base44's scalable architecture and automation tools to take your online presence to the next level.</li>\n</ul>\n\n<p><a href=\"https://base44.pxf.io/c/2252709/2049275/25619?trafcat=base\"><strong>Try Base44 free today.</strong></a></p>\nReady to take your online presence to the next level with Base44? Sign up for a free trial today and discover the power of advanced marketing strategies.",
  "audience": "seniors",
  "coverImage": "https://images.pexels.com/photos/6874545/pexels-photo-6874545.jpeg?auto=compress&cs=tinysrgb&h=350",
  "generatedAt": "2026-06-10T12:07:11.270Z"
}