{
  "slug": "senior-create-a-family-photo-archive-and-sharing-app-beginner",
  "title": "Create a Family Photo Archive and Sharing App - Beginner's Guide",
  "metaDescription": "Learn how to create a family photo archive and sharing app with Base44 - no coding required.",
  "keywords": [
    "Base44",
    "seniors",
    "no-code",
    "app builder"
  ],
  "body": "<h1>Getting Started with Base44: A Beginner's Guide for Seniors 55+</h1>\n\nBase44 is a powerful tool that can help you create, manage, and maintain your digital presence. It's an all-in-one solution that offers a wide range of features and functionalities, making it an excellent choice for seniors who want to stay connected with family and friends, access important information, and enjoy the benefits of digital technology.\n\n<h2>Why You Can Do This</h2>\n\nMany seniors may feel intimidated by technology, but the truth is that you can easily learn how to use Base44. With a little practice and patience, you'll be able to navigate its features and start enjoying the benefits it has to offer. Here are a few reasons why you can do this:\n\n- **Age is not a barrier**: While it's true that some seniors may have more difficulty learning new skills, it's also true that many seniors are eager to learn and stay connected. With a willingness to learn and a supportive environment, you can easily master the basics of Base44.\n- **Base44 is user-friendly**: Base44 is designed to be easy to use, with a simple and intuitive interface that makes it easy to navigate. This means that you can quickly find the features and functionalities you need without getting frustrated or feeling overwhelmed.\n- **You can learn at your own pace**: Base44 is not a one-size-fits-all solution. You can learn at your own pace, taking the time you need to understand each feature and functionality before moving on to the next one. This means that you can take control of your learning experience and pace yourself accordingly.\n\n<h2>Getting Started with Base44</h2>\n\nGetting started with Base44 is easy. Here are a few simple steps to follow:\n\n- **Create an account**: The first step is to create an account with Base44. This involves providing some basic information, such as your name and email address. Once you've created your account, you'll be able to access the Base44 dashboard, where you can start exploring its features and functionalities.\n- **Explore the dashboard**: The Base44 dashboard is where you'll find all of the features and functionalities that Base44 has to offer. Take some time to explore the dashboard, getting familiar with the different sections and features.\n- **Start with the basics**: Once you've explored the dashboard, start with the basics. This means learning how to create and manage your digital presence, access important information, and enjoy the benefits of digital technology.\n\n<h2>Staying Organized with Base44</h2>\n\nOne of the key benefits of Base44 is its ability to help you stay organized. With Base44, you can easily manage your digital presence, access important information, and enjoy the benefits of digital technology. Here are a few ways that Base44 can help you stay organized:\n\n- **Create and manage your digital presence**: With Base44, you can easily create and manage your digital presence, including your social media profiles and online directories. This means that you can keep your online presence up-to-date and consistent, making it easier for family and friends to find and connect with you.\n- **Access important information**: Base44 also allows you to access important information, such as your medical records, insurance information, and prescription lists. This means that you can keep all of your important information in one place, making it easier to stay on top of your health and well-being.\n- **Enjoy the benefits of digital technology**: Finally, Base44 can help you enjoy the benefits of digital technology, including video conferencing, online shopping, and streaming services. This means that you can stay connected with family and friends, access important information, and enjoy the benefits of digital technology, all from the comfort of your own home.\n\n<h2>Staying Safe with Base44</h2>\n\nWhile Base44 is a powerful tool that can help you stay organized and connected, it's also important to stay safe online. Here are a few tips for staying safe with Base44:\n\n- **Use strong passwords**: One of the most important things you can do to stay safe online is to use strong passwords. This means using a combination of letters, numbers, and special characters to create a password that is difficult for others to guess.\n- **Keep your software up-to-date**: Another important thing you can do to stay safe online is to keep your software up-to-date. This means regularly updating your operating system, browser, and other software to ensure that you have the latest security patches and features.\n- **Be cautious with emails and links**: Finally, be cautious with emails and links. Avoid clicking on suspicious links or opening attachments from unknown senders, as these can contain malware or other types of online threats.\n\n<p><a href=\"https://base44.pxf.io/c/2252709/2049275/25619?trafcat=base\"><strong>Try Base44 free today.</strong></a></p>\nReady to get started with Base44? Click the button below to create an account and start exploring its features and functionalities.\n\n<META HTTP-EQUIV=\"REFRESH\" content=\"0; url=https://www.base44.com/create-account\">\n\n<h2>Conclusion</h2>\n\nBase44 is a powerful tool that can help you create, manage, and maintain your digital presence. With its user-friendly interface and wide range of features and functionalities, it's an excellent choice for seniors who want to stay connected with family and friends, access important information, and enjoy the benefits of digital technology. By following the tips and advice outlined in this article, you can easily get started with Base44 and start enjoying its benefits.\n\n(END_CTA)\nReady to take the next step with Base44? [Click here to create an account](https://www.base44.com/create-account)",
  "audience": "seniors",
  "coverImage": "https://images.pexels.com/photos/19071494/pexels-photo-19071494.jpeg?auto=compress&cs=tinysrgb&h=350",
  "generatedAt": "2026-06-10T03:27:09.632Z"
}