{
  "slug": "senior-how-to-offer-online-courses-without-a-platform-advanced",
  "title": "How to Offer Online Courses Without a Platform - Advanced Strategies",
  "metaDescription": "Learn how to how to offer online courses without a platform with Base44 - no coding required.",
  "keywords": [
    "Base44",
    "seniors",
    "no-code",
    "app builder"
  ],
  "body": "<h1>Scaling Your Base44 Business: Advanced Strategies for Success</h1>\n\nAs a seasoned business owner, you've likely mastered the basics of running a successful Base44 operation. You've implemented effective marketing strategies, managed your finances, and honed your skills in automation and scaling. However, to take your business to the next level, it's essential to focus on advanced strategies that will propel you forward. In this article, we'll delve into the critical requirements for scaling your Base44 business, providing you with practical advice and actionable insights to help you achieve success.\n\n<h2>Why You Can Do This</h2>\n\nBefore we dive into the advanced strategies, it's essential to remind yourself that you have the skills, experience, and knowledge to succeed. As a senior business owner, you've already overcome numerous challenges and obstacles, and you've demonstrated your ability to adapt and evolve. This confidence and resilience will serve you well as you navigate the complexities of scaling your Base44 business.\n\n<h3>Section 1: Optimization and Refining Your Processes</h3>\n\nOne of the critical requirements for scaling your Base44 business is optimizing and refining your processes. This involves identifying areas where you can streamline operations, eliminate inefficiencies, and improve productivity. To achieve this, you'll need to:\n\n* Conduct a thorough analysis of your current processes and identify bottlenecks\n* Implement new technologies and tools to automate tasks and improve efficiency\n* Develop a robust project management system to track progress and stay organized\n* Continuously monitor and evaluate your processes, making adjustments as needed\n\nBy refining your processes, you'll be able to:\n\n* Reduce labor costs and increase productivity\n* Improve customer satisfaction and retention\n* Enhance your competitive edge and market share\n\n<h3>Section 2: Scaling Your Team and Operations</h3>\n\nAs your business grows, it's essential to scale your team and operations to meet the increased demands. This involves:\n\n* Developing a comprehensive talent acquisition and retention strategy\n* Implementing a robust onboarding process to ensure new team members are equipped to succeed\n* Creating a culture of continuous learning and professional development\n* Establishing clear goals, objectives, and performance metrics for your team\n\nBy scaling your team and operations, you'll be able to:\n\n* Increase capacity and meet growing demand\n* Enhance your ability to innovate and adapt to changing market conditions\n* Improve your overall competitiveness and market share\n\n<h3>Section 3: Advanced Automation and Integration</h3>\n\nAdvanced automation and integration are critical components of scaling your Base44 business. This involves leveraging cutting-edge technologies and tools to streamline operations, improve efficiency, and enhance customer experience. To achieve this, you'll need to:\n\n* Implement advanced automation tools, such as robotic process automation (RPA) and artificial intelligence (AI)\n* Develop a robust integration strategy to connect disparate systems and applications\n* Leverage data analytics and business intelligence to inform decision-making and drive growth\n\nBy harnessing the power of advanced automation and integration, you'll be able to:\n\n* Reduce labor costs and increase productivity\n* Improve customer satisfaction and retention\n* Enhance your competitive edge and market share\n\n<p><a href=\"https://base44.pxf.io/c/2252709/2049275/25619?trafcat=base\"><strong>Try Base44 free today.</strong></a></p>\nTake the first step towards scaling your Base44 business today. Our expert team is here to guide you every step of the way. Contact us to learn more about our advanced strategies and solutions.\n\n<h3>Section 4: Strategic Partnerships and Collaborations</h3>\n\nStrategic partnerships and collaborations are essential for scaling your Base44 business. This involves developing mutually beneficial relationships with other businesses, organizations, and individuals to drive growth, innovation, and profitability. To achieve this, you'll need to:\n\n* Identify potential partners and collaborators\n* Develop a robust partnership strategy to ensure mutually beneficial relationships\n* Establish clear goals, objectives, and performance metrics for partnerships\n* Continuously monitor and evaluate the effectiveness of partnerships\n\nBy forging strategic partnerships and collaborations, you'll be able to:\n\n* Increase access to new markets, customers, and revenue streams\n* Enhance your ability to innovate and adapt to changing market conditions\n* Improve your overall competitiveness and market share\n\n<h3>Section 5: Continuous Learning and Professional Development</h3>\n\nFinally, to scale your Base44 business, it's essential to prioritize continuous learning and professional development. This involves:\n\n* Developing a comprehensive learning strategy to stay up-to-date with the latest technologies, trends, and best practices\n* Encouraging a culture of continuous learning and professional development within your organization\n* Establishing clear goals, objectives, and performance metrics for learning and development\n* Continuously monitoring and evaluating the effectiveness of learning and development initiatives\n\nBy prioritizing continuous learning and professional development, you'll be able to:\n\n* Stay ahead of the competition and drive growth and innovation\n* Enhance your ability to adapt to changing market conditions\n* Improve your overall competitiveness and market share\n\n<p><a href=\"https://base44.pxf.io/c/2252709/2049275/25619?trafcat=base\"><strong>Try Base44 free today.</strong></a></p>\nTake the next step towards scaling your Base44 business today. With our expert guidance and support, you'll be able to achieve your goals and achieve success. Contact us to learn more about our advanced strategies and solutions.",
  "audience": "seniors",
  "coverImage": "https://images.pexels.com/photos/7983622/pexels-photo-7983622.jpeg?auto=compress&cs=tinysrgb&h=350",
  "generatedAt": "2026-06-10T03:35:39.264Z"
}